minimalkeys.py
minimalkeys-0.1.0.dist-info/LICENSE
minimalkeys-0.1.0.dist-info/WHEEL
minimalkeys-0.1.0.dist-info/METADATA
minimalkeys-0.1.0.dist-info/RECORD
