Metadata-Version: 1.2
Name: minimalkeys
Version: 0.1.0
Summary: Compute the minimal keys for a collection of strings or sequences.
Home-page: https://github.com/osteele/minimal-keys
License: UNKNOWN
Author: Oliver Steele
Author-email: steele@osteele.com
Requires-Python: >=3.5
Classifier: Development Status :: 3 - Alpha
Classifier: Intended Audience :: Developers
Classifier: License :: OSI Approved :: MIT License
Classifier: Programming Language :: Python
Classifier: Programming Language :: Python :: 3
Classifier: Programming Language :: Python :: 3.5
Classifier: Programming Language :: Python :: 3.6
